{
  "base_price": 2995,
  "beamstation_catalog_url": "https://beamstation.com/datasets",
  "beamstation_origin": "https://beamstation.com",
  "category_group_name": "Restaurants",
  "config_category": "email",
  "config_description": "--Reach Independent Inboxes--\n\nWeekly verified, high-deliverability emails.\n\nOnly for established, independent restaurants (or micro-chains) \u2013 large chain enterprises excluded.\n\nWeekly email verification and detailed analysis via our proprietary infrastructure.\n\nBusiness activity validated by an \"Active Heartbeat\" signal.",
  "config_name": "Restaurant Verified Email Access in Phoenix, Arizona, US",
  "export_job_id": "71b62958-1617-4111-8235-64d8c0adca7d",
  "github_org": "Beamstation-Datasets",
  "id_short": 402097,
  "location_name": "Phoenix",
  "location_type": "city",
  "repo_name": "restaurant-verified-email-access-in-phoenix-arizona-us-sample-402097",
  "sample_b2_path": "b2-export:BeamStation-ExportFiles/402097/beamstation_402097_restaurants-us-az_SAMPLE_DIST.csv",
  "sample_pct": 9.98,
  "sample_records": 80,
  "sample_sha256": "2a11c69dee1ad51f2116a50ae640e51469d62d1716dad4cbea8cbac6651ed2ae",
  "sample_size_bytes": 344703,
  "total_records": 802,
  "updated_at": "2026-04-15T04:18:19.327492+00:00"
}